pixell/lensing.py
pixell/_colorize.cpython-39-darwin.so
pixell/bunch.py
pixell/array_ops.py
pixell/srcsim.cpython-39-darwin.so
pixell/curvedsky.py
pixell/config.py
pixell/old_aberration.py
pixell/analysis.py
pixell/pointsrcs.py
pixell/enmap.py
pixell/resample.py
pixell/tilemap.py
pixell/memory.py
pixell/device.py
pixell/_array_ops_64.cpython-39-darwin.so
pixell/lib_distances_shared.a
pixell/__init__.py
pixell/enplot.py
pixell/_array_ops_32.cpython-39-darwin.so
pixell/uharm.py
pixell/warray.py
pixell/wavelets.py
pixell/coordsys.py
pixell/cmisc.cpython-39-darwin.so
pixell/lib_srcsim_shared.a
pixell/bench.py
pixell/powspec.py
pixell/mpiutils.py
pixell/interpol.py
pixell/multimap.py
pixell/arial.ttf
pixell/mpi.py
pixell/_interpol_32.cpython-39-darwin.so
pixell/utils.py
pixell/sites.py
pixell/_interpol_64.cpython-39-darwin.so
pixell/aberration.py
pixell/fft.py
pixell/colorize.py
pixell/reproject.py
pixell/distances.cpython-39-darwin.so
pixell/wcsutils.py
pixell/lib_cmisc_shared.a
pixell/cgrid.py
pixell/ephem.py
pixell/coordinates.py
pixell/colors.py
pixell/.dylibs/libgfortran.5.dylib
pixell/.dylibs/libquadmath.0.dylib
pixell/.dylibs/libgcc_s.1.1.dylib
pixell/.dylibs/libgomp.1.dylib
pixell/scripts/benchmark_pixell.py
pixell/scripts/benchmark_pixell_runner.py
pixell-0.31.3.dist-info/RECORD
pixell-0.31.3.dist-info/LICENSE
pixell-0.31.3.dist-info/WHEEL
pixell-0.31.3.dist-info/entry_points.txt
pixell-0.31.3.dist-info/METADATA
