Metadata-Version: 2.1
Name: pixell
Version: 0.31.3
Summary: A rectangular pixel map manipulation and harmonic analysis library derived from Sigurd Naess' enlib.
Author: Simons Observatory Collaboration Analysis Library Task Force
Maintainer-Email: Sigurd Naess <s.k.nass@astro.uio.no>, Mathew Madhavacheril <mathewsyriac@gmail.com>, Matthew Hasselfield <mhasselfield@flatironinstitute.org>, Josh Borrow <josh@joshborrow.com>
License: 
Requires-Python: >=3.9
Requires-Dist: numpy
Requires-Dist: astropy>=2.0
Requires-Dist: scipy>=1.0
Requires-Dist: matplotlib>=2.0
Requires-Dist: Pillow!=10.4.0,>=5.3.0
Requires-Dist: ducc0>=0.36.0
Requires-Dist: numba>=0.54.0
Requires-Dist: healpy>=1.13
Requires-Dist: python_dateutil>=2.7
Provides-Extra: test
Requires-Dist: pip>=9.0; extra == "test"
Requires-Dist: bumpversion>=0.5; extra == "test"
Requires-Dist: wheel>=0.30; extra == "test"
Requires-Dist: watchdog>=0.8; extra == "test"
Requires-Dist: flake8>=3.5; extra == "test"
Requires-Dist: coverage>=4.5; extra == "test"
Requires-Dist: Sphinx>=1.7; extra == "test"
Requires-Dist: twine>=1.10; extra == "test"
Requires-Dist: numpy; extra == "test"
Requires-Dist: astropy>=2.0; extra == "test"
Requires-Dist: setuptools>=39.2; extra == "test"
Requires-Dist: h5py>=3.12.1; extra == "test"
Requires-Dist: scipy>=1.0; extra == "test"
Requires-Dist: python_dateutil>=2.7; extra == "test"
Requires-Dist: cython; extra == "test"
Requires-Dist: matplotlib>=2.0; extra == "test"
Requires-Dist: pyyaml>=5.0; extra == "test"
Requires-Dist: pytest-cov>=2.6; extra == "test"
Requires-Dist: coveralls>=1.5; extra == "test"
Requires-Dist: pytest>=4.6; extra == "test"
